snapconsole/__init__.py
snapconsole/snapconsole.py
snapconsole/textbox.py
snapconsole/wrappedlist.py
snap_console-1.0.5.dist-info/LICENSE
snap_console-1.0.5.dist-info/METADATA
snap_console-1.0.5.dist-info/WHEEL
snap_console-1.0.5.dist-info/top_level.txt
snap_console-1.0.5.dist-info/RECORD
