Metadata-Version: 2.1
Name: snap-console
Version: 1.0.5
Summary: Easy-to-use interactive console for Python built on the curses library.
Home-page: https://github.com/Kenneth-LJS/snap-console
Author: Kenneth-LJS
Author-email: kenneth_ljs@live.com
Project-URL: Bug Tracker, https://github.com/Kenneth-LJS/snap-console/issues
Classifier: Development Status :: 5 - Production/Stable
Classifier: License :: OSI Approved :: MIT License
Classifier: Environment :: Console
Classifier: Environment :: Console :: Curses
Classifier: Programming Language :: Python :: 3
Classifier: Programming Language :: Python :: 3.7
Classifier: Programming Language :: Python :: 3.8
Classifier: Programming Language :: Python :: 3.9
Classifier: Programming Language :: Python :: 3.10
Classifier: Operating System :: Microsoft :: Windows
Requires-Python: >=3.7
License-File: LICENSE
